{
  "page_name": "הלוואה להשקעה באישור מיידי ובריבית נמוכה",
  "keyword": "הלוואות להשקעה",
  "url": "https://loan-israel.co.il/%d7%94%d7%9c%d7%95%d7%95%d7%90%d7%95%d7%aa-%d7%9c%d7%94%d7%a9%d7%a7%d7%a2%d7%94/",
  "post_id": "1524",
  "site": "main",
  "title": "הלוואות להשקעה באישור מיידי ובריבית נמוכה - ✔️ רק תבקש",
  "description": "רוצים הלוואה למטרת השקעה? היכנסו לפורטל רק תבקש וקבלו מגוון אפשרויות ופתרונות מימון בהלוואות להשקעות בתנאים שמתאימים לכם.",
  "word_count": 1307,
  "is_special": false,
  "imported_at": "2026-01-06T11:45:38.823568",
  "fetched_keywords": {},
  "last_upload": "2026-01-08T11:54:09.271Z",
  "last_upload_type": "content"
}