{
  "page_name": "הלוואה ללא ריבית לכל מטרה באישור מיידי",
  "keyword": "הלוואה ללא ריבית",
  "url": "https://loan-israel.co.il/%d7%94%d7%9c%d7%95%d7%95%d7%90%d7%95%d7%aa-%d7%9c%d7%9c%d7%90-%d7%a8%d7%99%d7%91%d7%99%d7%aa/",
  "post_id": "96",
  "site": "main",
  "title": "הלוואה ללא ריבית לכל מטרה באישור מיידי - ✔️ רק תבקש",
  "description": "אם חשבתם שכיום כבר לא ניתן למצוא הלוואה בתנאים נוחים, תחשבו שוב! פורטל ההלוואות רק תבקש מרכז עבורכם מידע בנוגע למגוון הלוואות ללא ריבית והחזרים גמישים ונוחים. היכנסו לאתר לקריאה ותהנו מבדיקת זכאות ללא עלות!",
  "word_count": 1919,
  "is_special": false,
  "imported_at": "2026-01-06T11:45:18.043497",
  "fetched_keywords": {},
  "last_upload": "2026-01-07T10:18:35.031Z",
  "last_upload_type": "content"
}