{
  "archived_at": "2026-01-13T11:12:23.647624",
  "reason": "archived",
  "original_path": "דפים לשינוי\\business\\הלוואות בערבות מדינה מסלול הון חוזר\\הלוואות בערבות מדינה מסלול הון חוזר.html",
  "metadata": {
    "wordpress_id": "2671",
    "url": "https://loan-israel.co.il/Business/maslol-hon-huzer/",
    "site": "business",
    "original_status": "publish",
    "redirect_type": "301",
    "redirect_target": "https://loan-israel.co.il/Business/working-capital-loans/",
    "redirect_id": null
  }
}