{
  "page_name": "הלוואה עד 90,000 ש&quot;ח באישור מיידי",
  "keyword": "הלוואה עד 90000 שח",
  "url": "https://loan-israel.co.il/%d7%94%d7%9c%d7%95%d7%95%d7%90%d7%94-%d7%a2%d7%93-90000-%d7%a9%d7%97/",
  "post_id": "2612",
  "site": "main",
  "title": "הלוואה עד 90,000 ש\"ח באישור מיידי - ✔️ רק תבקש",
  "description": "המומחים של רק תבקש הלוואות לכל מטרה יסייעו לך לקבל הלוואות של 90,000 שקל בתנאים הנוחים והטובים ביותר. היכנס לאתר למידע נוסף וקבל הצעה אטרקטיבית להלוואה.",
  "word_count": 1969,
  "is_special": false,
  "imported_at": "2026-01-06T11:47:37.776183",
  "fetched_keywords": {},
  "last_upload": "2026-01-07T12:35:22.787Z",
  "last_upload_type": "content"
}