{
  "keyword": "מימון לקולטים סולארים",
  "url": "https://loan-israel.co.il/Business/solar-activity-financing-plan/",
  "post_id": "1620",
  "site": "business",
  "title": "תכנית מימון לפעילות סולארית - הלוואות בערבות המדינה ובנקים באישור מיידי",
  "description": "פעילות סולארית היא תחום בעל פוטנציאל גבוה של צמיחה וכעת ישנה אפשרות לקבל מימון לפעילות בתחום מהבנק הסיני לפיתוח. קרא באתר רק תבקש על האפשרויות למימון פעילות סולארית.",
  "imported_at": "2026-01-03T13:58:56.862789",
  "fetched_keywords": {
    "timestamp": "2026-01-13T07:48:48.833Z",
    "main_keyword": "מימון לקולטים סולארים",
    "clusters": [
      {
        "primary": "מימון לקולטים סולארים מחיר",
        "source": "autocomplete",
        "type": "unique",
        "unique_part": "מחיר",
        "variants": []
      },
      {
        "primary": "מימון לקולטים סולארים לרכב",
        "source": "autocomplete",
        "type": "unique",
        "unique_part": "לרכב",
        "variants": []
      },
      {
        "primary": "מימון לקולטים סולארים לגינה",
        "source": "autocomplete",
        "type": "unique",
        "unique_part": "לגינה",
        "variants": []
      },
      {
        "primary": "מערכת סולארית ביתית",
        "source": "related",
        "type": "unique",
        "unique_part": "מערכת סולארית ביתית",
        "variants": []
      },
      {
        "primary": "מימון אנרגיה ירוקה",
        "source": "related",
        "type": "unique",
        "unique_part": "אנרגיה ירוקה",
        "variants": []
      },
      {
        "primary": "רעפים סולאריים",
        "source": "related",
        "type": "unique",
        "unique_part": "רעפים סולאריים",
        "variants": []
      },
      {
        "primary": "השקעה בלוחות סולאריים",
        "source": "related",
        "type": "unique",
        "unique_part": "השקעה בלוחות סולאריים",
        "variants": []
      }
    ],
    "final_keywords": [
      "מימון לקולטים סולארים מחיר",
      "מימון לקולטים סולארים לרכב",
      "מימון לקולטים סולארים לגינה",
      "מערכת סולארית ביתית",
      "מימון אנרגיה ירוקה",
      "רעפים סולאריים",
      "השקעה בלוחות סולאריים"
    ],
    "unique_topics": [
      "מחיר",
      "לרכב",
      "לגינה",
      "מערכת סולארית ביתית",
      "אנרגיה ירוקה",
      "רעפים סולאריים",
      "מחשבון הלוואה",
      "השקעה בלוחות סולאריים",
      "מחשבון הלוואה לאומי",
      "בנק לאומי הלוואה ללא ריבית 70000",
      "הלוואה לטווח ארוך"
    ],
    "rank_position": null,
    "rank_checked_url": "https://loan-israel.co.il/Business/solar-activity-financing-plan/",
    "organic_results": [
      {
        "description": "סכום ההלוואה: עד 100% מעלות המערכת הסולארית או עד 100 אלף ש\"ח (הנמוך מבינהם) · תקופת ההלוואה: עד 10 שנים (עד 120 תשלומים) · גרייס על הקרן (דחיית תחילת התשלום): עד ...",
        "displayedUrl": "https://www.bankhapoalim.co.il › דף הבית › הלוואות",
        "position": 1,
        "title": "אשראי סולארי- הלוואה להתקנת מערכת ביתית",
        "url": "https://www.bankhapoalim.co.il/he/loans/solar-system"
      },
      {
        "description": "סכום ההלוואה: עד 100% מימון (בהתאם לעלות המערכת, ניתן לקבל מימון נוסף ברכישה של יותר ממערכת אחת). · תנאי ההלוואה: לתקופה של עד 20 שנים, בריבית פריים או ריבית ...",
        "displayedUrl": "https://www.leumi.co.il › solar-energy-loan",
        "position": 2,
        "title": "הלוואה להקמת מתקן סולארי",
        "url": "https://www.leumi.co.il/he/solar-energy-loan"
      },
      {
        "description": "בנק מרכנתיל מציע הלוואה של עד 100,000 ש\"ח עם פריסה של 120 תשלומים, כלומר 10 שנים. וכדאי לבקש הצעה בהתאם לתקופת ההחזר שאתם מעריכים שתצטרכו. כמובן שתמיד כדאי ...",
        "displayedUrl": "https://solarcell.co.il › עידכונים סולארים › כללי",
        "position": 3,
        "title": "מימון בנקאי של מערכות סולאריות - חשמל סולארי",
        "url": "https://solarcell.co.il/08/%D7%9E%D7%99%D7%9E%D7%95%D7%9F-%D7%91%D7%A0%D7%A7%D7%90%D7%99-%D7%A9%D7%9C-%D7%9E%D7%A2%D7%A8%D7%9B%D7%95%D7%AA-%D7%A1%D7%95%D7%9C%D7%90%D7%A8%D7%99%D7%95%D7%AA/"
      },
      {
        "description": "מזרחי-טפחות מציע לך להפוך את גג ביתך לאקולוגי יותר וכל זה בהלוואה בתנאים משתלמים במיוחד!",
        "displayedUrl": "https://www.mizrahi-tefahot.co.il › loans › privateloanslib",
        "position": 4,
        "title": "הלוואה למימון מתקנים סולאריים | בנק מזרחי-טפחות",
        "url": "https://www.mizrahi-tefahot.co.il/loans/privateloanslib/financing-solar-installations-loan/"
      },
      {
        "description": "עד 100,000 ₪ או 100% מימון משווי המערכת הסולארית (כולל מימון מערכת האגירה) - הנמוך מביניהם. · פריסת תשלומים ארוכה - עד 96 תשלומים חודשיים! · אפשרות לתחילת תשלום ...",
        "displayedUrl": "https://www.mercantile.co.il › loans › solar-roofs",
        "position": 5,
        "title": "הלוואה להתקנת מערכת סולארית",
        "url": "https://www.mercantile.co.il/private/loans/solar-roofs/"
      },
      {
        "description": "מימון מערכות סולאריות · מסלול רכישה פרטי: מסלול זה מתאים למי שמעוניין להשקיע באופן עצמאי במערכת סולארית. · מסלול השכרה (ליסינג): במסלול זה, החברה מקימה את המערכת ...",
        "displayedUrl": "https://hod-eng.com › מסלולי-מימון-למערכות-סולאריות",
        "position": 6,
        "title": "מסלולי מימון למערכות סולאריות",
        "url": "https://hod-eng.com/%D7%9E%D7%A1%D7%9C%D7%95%D7%9C%D7%99-%D7%9E%D7%99%D7%9E%D7%95%D7%9F-%D7%9C%D7%9E%D7%A2%D7%A8%D7%9B%D7%95%D7%AA-%D7%A1%D7%95%D7%9C%D7%90%D7%A8%D7%99%D7%95%D7%AA/"
      },
      {
        "description": "מהם מסלולי המימון הסולארי הקיימים למימון מערכת סולארית? אילו אפשרויות מימון מציעה וולטה סולאר? וכיצד זה יכול לעזור לנו? כל התשובות במקום אחד >",
        "displayedUrl": "https://volta.solar › מרכז למידה",
        "position": 7,
        "title": "מימון מערכת סולארית: מסלולי המימון של מערכות סולאריות",
        "url": "https://volta.solar/knowledge-center/%D7%9E%D7%94%D7%9D-%D7%9E%D7%A1%D7%9C%D7%95%D7%9C%D7%99-%D7%94%D7%9E%D7%99%D7%9E%D7%95%D7%9F-%D7%94%D7%A7%D7%99%D7%99%D7%9E%D7%99%D7%9D-%D7%A2%D7%A1%D7%A7%D7%99/"
      },
      {
        "description": "מסלול ראשון: מימון בנקאי · +10 שנות מימון · השתתפות עצמית של כ-10% · ריבית החלה מפריים+1.2% · גרייס של 6 חודשים או יותר.",
        "displayedUrl": "https://kedmasolar.com › מימון",
        "position": 8,
        "title": "מימון למערכת סולארית",
        "url": "https://kedmasolar.com/%D7%9E%D7%99%D7%9E%D7%95%D7%9F/"
      },
      {
        "description": "מי שיש בבעלותו את השטח הדרוש להתקנת מערכות סולאריות ואינו חפץ או שאינו יכול לעשות שימוש בהונו האישי, יכול לקבל מימון מערכות סולאריות בסך של עד 100% מעלות רכישת ...",
        "displayedUrl": "https://www.solarise.co.il › מימון-מערכות-סולאריות",
        "position": 9,
        "title": "מימון מערכות סולאריות? המומחים של סולארייז כאן עם כל התשובות",
        "url": "https://www.solarise.co.il/%D7%9E%D7%99%D7%9E%D7%95%D7%9F-%D7%9E%D7%A2%D7%A8%D7%9B%D7%95%D7%AA-%D7%A1%D7%95%D7%9C%D7%90%D7%A8%D7%99%D7%95%D7%AA/"
      },
      {
        "description": "4 בפבר׳ 2025 — האתר יאפשר לכל בעל נכס לדעת את פוטנציאל הייצור הסולארי על הגג שלו, הערכה של הספק החשמל שניתן להפיק מהתקנת פנלים סולאריים וכמו כן, יסייע לרשויות ...",
        "displayedUrl": "https://www.gov.il › pages › news-040225",
        "position": 10,
        "title": "יש חדש תחת השמש: מהיום תוכלו לדעת כמה אתם יכולים להרוויח מהגג ...",
        "url": "https://www.gov.il/he/pages/news-040225"
      }
    ],
    "ai_mode_results": [
      {
        "description": "נכון לשנת 2026, קיימות מגוון אפשרויות מימון והטבות להתקנת קולטים (פאנלים) סולאריים בישראל, המיועדות להפוך את ההשקעה לנגישה ומשתלמת: 1. מימון בנקאי (הלוואות ייעודיות) הבנקים בישראל רואים במערכות סולאריות השקעה בטוחה ומציעים מסלולי מימון נוחים: מימון של עד 100%: רוב הבנקים הגדולים, כגון בנק לאומי, בנק הפועלים ומזרחי-טפחות, מציעים הלוואות ייעודיות ללקוחות פרטיים ועסקיים לכיסוי מלא של עלויות ההקמה.החזר מהכנסות המערכת: מבנה ההלוואה לרוב מאפשר להחזיר את התשלומים החודשיים ישירות מהרווחים שמייצרת המערכת ממכירת החשמל.תקופת החזר: ההלוואות ניתנות לרוב לתקופות של עד 10 שנים, כאשר זמן ההחזר הממוצע (Break-even) עומד על כ-5 עד 6 שנים לבתים פרטיים. 2. תמריצים ממשלתיים וסובסידיות המדינה מעודדת התקנה על גגות באמצעות הטבות כלכליות: פטור ממס: קיים פטור ממס הכנסה על הכנסות ממכירת חשמל ממערכת ביתית עד לתקרה שנתית (נכון ל-2025/26 מדובר בכ-24,000-25,000 ש\"ח).תעריף ייצור מובטח: חברת החשמל מתחייבת לרכוש את החשמל המיוצר בתעריף קבוע וידוע מראש למשך 25 שנה, מה שמבטיח תשואה יציבה של כ-15% בשנה.מענקים לאגירה: בשנת 2026 קיימות סובסידיות (כ-5,000 ש\"ח) לרכישת סוללות אגירה, המאפשרות להשתמש בחשמל גם בשעות הלילה או בזמן הפסקות חשמל. 3. מודלים עסקיים ללא עלות ראשונית למי שאינו מעוניין לקחת הלוואה או להשקיע הון עצמי: השכרת גג: חברות סולאריות שוכרות את שטח הגג מבעל הנכס, מתקינות ומפעילות את המערכת על חשבונן, ומשלמות לבעל הגג דמי שכירות חודשיים או מספקות לו חשמל מוזל.שותפות ברווחים: מודל בו החברה המקימה מממנת את המערכת ומתחלקת ברווחי מכירת החשמל עם בעל הגג למשך תקופה מוסכמת. 4. חובת התקנה בבנייה חדשה החל משנת 2026, קיימת רגולציה המחייבת התקנת פאנלים סולאריים בכל בניין מגורים חדש (גגות מעל 100 מ\"ר) ומבני ציבור, מה שהופך את המימון לחלק בלתי נפרד מעלויות הבנייה או המשכנתא.",
        "is_summary": true,
        "position": 0,
        "title": "AI Overview Summary",
        "url": ""
      },
      {
        "description": "Feb 18, 2025 — Faster repayment of loans. Banks are offering 100% loans for solar systems, which they regard as a safe investment. On February 25...",
        "position": 1,
        "title": "Invest in solar panels, enjoy 15% annual return for 25 years",
        "url": "https://www.timesofisrael.com/energy-ministry-invest-in-solar-panels-enjoy-15-annual-return-for-25-years/#:~:text=Faster%20repayment%20of%20loans,to%20the%20consumer%20price%20index."
      },
      {
        "description": "Aug 1, 2023 — well that running cool air doesn't come cheap and puts a major dent in your wallet. and that's the effects of climate change becom...",
        "position": 2,
        "title": "Start up rents rooftops for solar panels, giving Israelis cheap ...",
        "url": "https://www.youtube.com/watch?v=hu2OEZlXMmw&t=13"
      },
      {
        "description": "Apr 1, 2025 — To encourage the installation of rooftop solar panels, Israel is introducing new incentives, including tax breaks for homeowners, ...",
        "position": 3,
        "title": "Israel Solar Incentives: New Tax Breaks for Homeowners",
        "url": "https://www.pvknowhow.com/news/rooftop-solar-incentives-israel-new-panels/#:~:text=To%20encourage%20the%20installation%20of,things%20they%20don't%20need!"
      },
      {
        "description": "Feb 18, 2025 — Energy Ministry: Invest in solar panels, enjoy 15% annual return for 25 years | The Times of Israel. © 2026 The Times of Israel , ...",
        "position": 4,
        "title": "Invest in solar panels, enjoy 15% annual return for 25 years",
        "url": "https://www.timesofisrael.com/energy-ministry-invest-in-solar-panels-enjoy-15-annual-return-for-25-years/#:~:text=Energy%20Ministry:%20Invest%20in%20solar,electricity%20from%20renewables%20by%202030."
      },
      {
        "description": "Jan 30, 2025 — The Israel Electric Corporation's plan for expanding the distribution grid carries a price tag of NIS 20 billion ($5.6 billion) Th...",
        "position": 5,
        "title": "Solar panel installations must grow by 40% to meet 2030 goals",
        "url": "https://www.timesofisrael.com/solar-panel-installations-need-to-grow-by-40-to-meet-2030-goals-energy-ministry/#:~:text=The%20Israel%20Electric%20Corporation's%20plan,Israel%20and%20the%20Jewish%20world."
      },
      {
        "description": "Dec 9, 2025 — The ministry hopes the plan will go into effect for all new residential buildings in Israel during 2026. By 2030, Israel could hav...",
        "position": 6,
        "title": "New plan looks to replace Israel's solar water heaters with PV cells ...",
        "url": "https://www.timesofisrael.com/new-plan-looks-to-replace-israels-solar-water-heaters-with-pv-cells-and-heat-pumps/#:~:text=The%20ministry%20hopes%20the%20plan,and%20financially%20support%20our%20work."
      },
      {
        "description": "Dec 17, 2025 — For property owners, the financial returns from solar panel installations are highly appealing. The Israeli government has introdu...",
        "position": 7,
        "title": "Israel: Solar PV Mandated for New Residential Buildings with ...",
        "url": "https://www.powerack.com/israel-solar-pv-mandated-for-new-residential-buildings-with-annual-roi-up-to-15#:~:text=For%20property%20owners%2C%20the%20financial,in%20ROI%20in%20later%20years."
      },
      {
        "description": "* הלוואות * אשראי סולארי הלוואה להתקנת מערכת ביתית",
        "position": 8,
        "title": "אשראי סולארי- הלוואה להתקנת מערכת ביתית - בנק הפועלים",
        "url": "https://www.bankhapoalim.co.il/he/loans/solar-system#:~:text=*%20%D7%94%D7%9C%D7%95%D7%95%D7%90%D7%95%D7%AA%20*%20%D7%90%D7%A9%D7%A8%D7%90%D7%99%20%D7%A1%D7%95%D7%9C%D7%90%D7%A8%D7%99%20%D7%94%D7%9C%D7%95%D7%95%D7%90%D7%94%20%D7%9C%D7%94%D7%AA%D7%A7%D7%A0%D7%AA%20%D7%9E%D7%A2%D7%A8%D7%9B%D7%AA%20%D7%91%D7%99%D7%AA%D7%99%D7%AA"
      },
      {
        "description": "הלוואה להקמת מתקן סולארי - בנק לאומי",
        "position": 9,
        "title": "הלוואה להקמת מתקן סולארי - בנק לאומי",
        "url": "https://www.leumi.co.il/he/solar-energy-loan#:~:text=%D7%94%D7%9C%D7%95%D7%95%D7%90%D7%94%20%D7%9C%D7%94%D7%A7%D7%9E%D7%AA%20%D7%9E%D7%AA%D7%A7%D7%9F%20%D7%A1%D7%95%D7%9C%D7%90%D7%A8%D7%99%20%2D%20%D7%91%D7%A0%D7%A7%20%D7%9C%D7%90%D7%95%D7%9E%D7%99"
      },
      {
        "description": "הלוואות; הלוואה להקמת מתקן סולארי ללקוחות פרטיים. הלוואה להקמת מתקן סולארי ללקוחות פרטיים. הידעתם שהגג שלכם יכול להרוויח עבורכם? ב...",
        "position": 10,
        "title": "הלוואה להקמת מתקן סולארי ללקוחות פרטיים - בנק לאומי",
        "url": "https://www.leumi.co.il/he/credit/loans/solar_private"
      },
      {
        "description": "Aug 8, 2011 — * כמה זמן לוקח להתקין מערכת סולארית? האם המערכת הסולארית פטורה ממס? מי יכול להתקין מערכת סולארית? * אנרגיה ירוקה * עלות",
        "position": 11,
        "title": "מימון בנקאי של מערכות סולאריות - חשמל סולארי",
        "url": "https://solarcell.co.il/08/%D7%9E%D7%99%D7%9E%D7%95%D7%9F-%D7%91%D7%A0%D7%A7%D7%90%D7%99-%D7%A9%D7%9C-%D7%9E%D7%A2%D7%A8%D7%9B%D7%95%D7%AA-%D7%A1%D7%95%D7%9C%D7%90%D7%A8%D7%99%D7%95%D7%AA/"
      },
      {
        "description": "מימון מערכת סולארית: מסלולי המימון של מערכות סולאריות | Volta Solar.",
        "position": 12,
        "title": "מימון מערכת סולארית: מסלולי המימון של מערכות סולאריות",
        "url": "https://volta.solar/knowledge-center/%D7%9E%D7%94%D7%9D-%D7%9E%D7%A1%D7%9C%D7%95%D7%9C%D7%99-%D7%94%D7%9E%D7%99%D7%9E%D7%95%D7%9F-%D7%94%D7%A7%D7%99%D7%99%D7%9E%D7%99%D7%9D-%D7%A2%D7%A1%D7%A7%D7%99/#:~:text=%D7%9E%D7%99%D7%9E%D7%95%D7%9F%20%D7%9E%D7%A2%D7%A8%D7%9B%D7%AA%20%D7%A1%D7%95%D7%9C%D7%90%D7%A8%D7%99%D7%AA:%20%D7%9E%D7%A1%D7%9C%D7%95%D7%9C%D7%99%20%D7%94%D7%9E%D7%99%D7%9E%D7%95%D7%9F%20%D7%A9%D7%9C%20%D7%9E%D7%A2%D7%A8%D7%9B%D7%95%D7%AA%20%D7%A1%D7%95%D7%9C%D7%90%D7%A8%D7%99%D7%95%D7%AA%20%7C%20Volta%20Solar"
      },
      {
        "description": "Dec 22, 2025 — To enhance energy utilization efficiency, energy storage batteries can be added as an optional feature. These batteries can increa...",
        "position": 13,
        "title": "Israel: Mandatory Solar Panel Installation for New Homes ...",
        "url": "https://www.solarbeglobal.com/israel-mandatory-solar-panel-installation-for-new-homes-offering-up-to-15-annual-return/#:~:text=To%20enhance%20energy%20utilization%20efficiency,return%20of%20up%20to%2015%25."
      }
    ],
    "ai_rank_position": null,
    "competitor_data": [
      {
        "description": "סכום ההלוואה: עד 100% מעלות המערכת הסולארית או עד 100 אלף ש\"ח (הנמוך מבינהם) · תקופת ההלוואה: עד 10 שנים (עד 120 תשלומים) · גרייס על הקרן (דחיית תחילת התשלום): עד ...",
        "position": 1,
        "title": "אשראי סולארי- הלוואה להתקנת מערכת ביתית",
        "url": "https://www.bankhapoalim.co.il/he/loans/solar-system"
      },
      {
        "description": "סכום ההלוואה: עד 100% מימון (בהתאם לעלות המערכת, ניתן לקבל מימון נוסף ברכישה של יותר ממערכת אחת). · תנאי ההלוואה: לתקופה של עד 20 שנים, בריבית פריים או ריבית ...",
        "position": 2,
        "title": "הלוואה להקמת מתקן סולארי",
        "url": "https://www.leumi.co.il/he/solar-energy-loan"
      },
      {
        "description": "בנק מרכנתיל מציע הלוואה של עד 100,000 ש\"ח עם פריסה של 120 תשלומים, כלומר 10 שנים. וכדאי לבקש הצעה בהתאם לתקופת ההחזר שאתם מעריכים שתצטרכו. כמובן שתמיד כדאי ...",
        "position": 3,
        "title": "מימון בנקאי של מערכות סולאריות - חשמל סולארי",
        "url": "https://solarcell.co.il/08/%D7%9E%D7%99%D7%9E%D7%95%D7%9F-%D7%91%D7%A0%D7%A7%D7%90%D7%99-%D7%A9%D7%9C-%D7%9E%D7%A2%D7%A8%D7%9B%D7%95%D7%AA-%D7%A1%D7%95%D7%9C%D7%90%D7%A8%D7%99%D7%95%D7%AA/"
      },
      {
        "description": "מזרחי-טפחות מציע לך להפוך את גג ביתך לאקולוגי יותר וכל זה בהלוואה בתנאים משתלמים במיוחד!",
        "position": 4,
        "title": "הלוואה למימון מתקנים סולאריים | בנק מזרחי-טפחות",
        "url": "https://www.mizrahi-tefahot.co.il/loans/privateloanslib/financing-solar-installations-loan/"
      },
      {
        "description": "עד 100,000 ₪ או 100% מימון משווי המערכת הסולארית (כולל מימון מערכת האגירה) - הנמוך מביניהם. · פריסת תשלומים ארוכה - עד 96 תשלומים חודשיים! · אפשרות לתחילת תשלום ...",
        "position": 5,
        "title": "הלוואה להתקנת מערכת סולארית",
        "url": "https://www.mercantile.co.il/private/loans/solar-roofs/"
      },
      {
        "description": "מימון מערכות סולאריות · מסלול רכישה פרטי: מסלול זה מתאים למי שמעוניין להשקיע באופן עצמאי במערכת סולארית. · מסלול השכרה (ליסינג): במסלול זה, החברה מקימה את המערכת ...",
        "position": 6,
        "title": "מסלולי מימון למערכות סולאריות",
        "url": "https://hod-eng.com/%D7%9E%D7%A1%D7%9C%D7%95%D7%9C%D7%99-%D7%9E%D7%99%D7%9E%D7%95%D7%9F-%D7%9C%D7%9E%D7%A2%D7%A8%D7%9B%D7%95%D7%AA-%D7%A1%D7%95%D7%9C%D7%90%D7%A8%D7%99%D7%95%D7%AA/"
      },
      {
        "description": "מהם מסלולי המימון הסולארי הקיימים למימון מערכת סולארית? אילו אפשרויות מימון מציעה וולטה סולאר? וכיצד זה יכול לעזור לנו? כל התשובות במקום אחד >",
        "position": 7,
        "title": "מימון מערכת סולארית: מסלולי המימון של מערכות סולאריות",
        "url": "https://volta.solar/knowledge-center/%D7%9E%D7%94%D7%9D-%D7%9E%D7%A1%D7%9C%D7%95%D7%9C%D7%99-%D7%94%D7%9E%D7%99%D7%9E%D7%95%D7%9F-%D7%94%D7%A7%D7%99%D7%99%D7%9E%D7%99%D7%9D-%D7%A2%D7%A1%D7%A7%D7%99/"
      },
      {
        "description": "מסלול ראשון: מימון בנקאי · +10 שנות מימון · השתתפות עצמית של כ-10% · ריבית החלה מפריים+1.2% · גרייס של 6 חודשים או יותר.",
        "position": 8,
        "title": "מימון למערכת סולארית",
        "url": "https://kedmasolar.com/%D7%9E%D7%99%D7%9E%D7%95%D7%9F/"
      },
      {
        "description": "מי שיש בבעלותו את השטח הדרוש להתקנת מערכות סולאריות ואינו חפץ או שאינו יכול לעשות שימוש בהונו האישי, יכול לקבל מימון מערכות סולאריות בסך של עד 100% מעלות רכישת ...",
        "position": 9,
        "title": "מימון מערכות סולאריות? המומחים של סולארייז כאן עם כל התשובות",
        "url": "https://www.solarise.co.il/%D7%9E%D7%99%D7%9E%D7%95%D7%9F-%D7%9E%D7%A2%D7%A8%D7%9B%D7%95%D7%AA-%D7%A1%D7%95%D7%9C%D7%90%D7%A8%D7%99%D7%95%D7%AA/"
      },
      {
        "description": "4 בפבר׳ 2025 — האתר יאפשר לכל בעל נכס לדעת את פוטנציאל הייצור הסולארי על הגג שלו, הערכה של הספק החשמל שניתן להפיק מהתקנת פנלים סולאריים וכמו כן, יסייע לרשויות ...",
        "position": 10,
        "title": "יש חדש תחת השמש: מהיום תוכלו לדעת כמה אתם יכולים להרוויח מהגג ...",
        "url": "https://www.gov.il/he/pages/news-040225"
      }
    ]
  },
  "word_count": 369,
  "wp_post_title": "תכנית מימון לפעילות סולארית",
  "page_name": "תכנית מימון לפעילות סולארית",
  "is_special": true
}