{
  "keyword": "קרן סיוע למסחר",
  "url": "https://loan-israel.co.il/Business/trade-relief-fund/",
  "post_id": "1876",
  "site": "business",
  "title": "קרן סיוע למסחר - הלוואות בערבות המדינה ובנקים באישור מיידי",
  "description": "עוסקים במסחר בארץ או בחו\"ל ומעוניינים לקבל סיוע של קרן סיוע למסחר של המדינה? היכנסו לאתר רק תבקש לעסקים והמומחים שלנו יסייעו לכם לקבל את הסיוע המשתלם ביותר",
  "imported_at": "2026-01-03T13:59:18.731800",
  "fetched_keywords": {
    "timestamp": "2026-01-03T14:16:04.660Z",
    "main_keyword": "קרן סיוע למסחר",
    "clusters": [
      {
        "primary": "קרן סיוע למסחר מילואים",
        "source": "autocomplete",
        "type": "unique",
        "unique_part": "מילואים",
        "variants": []
      },
      {
        "primary": "הלוואה בערבות המדינה gov",
        "source": "related",
        "type": "unique",
        "unique_part": "הלוואה בערבות המדינה gov",
        "variants": []
      },
      {
        "primary": "הלוואות בערבות מדינה ללא ריבית",
        "source": "related",
        "type": "unique",
        "unique_part": "הלוואות בערבות מדינה ללא ריבית",
        "variants": []
      },
      {
        "primary": "הלוואה בערבות המדינה בנק לאומי",
        "source": "related",
        "type": "unique",
        "unique_part": "הלוואה בערבות המדינה בנק לאומי",
        "variants": []
      },
      {
        "primary": "קרן בערבות המדינה",
        "source": "related",
        "type": "unique",
        "unique_part": "בערבות המדינה",
        "variants": []
      },
      {
        "primary": "קרן היערכות לעסקים במצב חירום",
        "source": "related",
        "type": "unique",
        "unique_part": "היערכות לעסקים במצב חירום",
        "variants": []
      },
      {
        "primary": "הקרן לעסקים קטנים",
        "source": "related",
        "type": "unique",
        "unique_part": "הקרן לעסקים קטנים",
        "variants": []
      },
      {
        "primary": "הלוואה בערבות המדינה חרבות ברזל",
        "source": "related",
        "type": "unique",
        "unique_part": "הלוואה בערבות המדינה חרבות ברזל",
        "variants": []
      },
      {
        "primary": "הלוואה בערבות מדינה לשכירים",
        "source": "related",
        "type": "unique",
        "unique_part": "הלוואה בערבות מדינה לשכירים",
        "variants": []
      }
    ],
    "final_keywords": [
      "קרן סיוע למסחר מילואים",
      "הלוואה בערבות המדינה gov",
      "הלוואות בערבות מדינה ללא ריבית",
      "הלוואה בערבות המדינה בנק לאומי",
      "קרן בערבות המדינה",
      "קרן היערכות לעסקים במצב חירום",
      "הקרן לעסקים קטנים",
      "הלוואה בערבות המדינה חרבות ברזל",
      "הלוואה בערבות מדינה לשכירים"
    ],
    "unique_topics": [
      "מילואים",
      "הלוואה בערבות המדינה gov",
      "הלוואות בערבות מדינה ללא ריבית",
      "הלוואה בערבות המדינה בנק לאומי",
      "בערבות המדינה",
      "היערכות לעסקים במצב חירום",
      "הקרן לעסקים קטנים",
      "הלוואה בערבות המדינה חרבות ברזל",
      "הלוואה בערבות מדינה לשכירים"
    ],
    "rank_position": 4,
    "rank_checked_url": "https://loan-israel.co.il/Business/trade-relief-fund/",
    "organic_results": [
      {
        "description": "המידע המלא והמדויק לעניין סוגי ההלוואות שניתן לקחת במסגרת הקרן, תנאי הסף לקבלת הלוואה בקרן והתהליך הנדרש לקבלת הלוואה יתקבל במהלך תהליך הגשת הבקשה ובחינתה, על ...",
        "displayedUrl": "https://govextra.gov.il › mof-gloans",
        "position": 1,
        "title": "קרן ההלוואות לעסקים קטנים ובינוניים בערבות מדינה - govextra",
        "url": "https://govextra.gov.il/mof-gloans/homepage/"
      },
      {
        "description": "הסוכנות לעסקים קטנים ובינוניים מסייעת באמצעות הלוואות לעסקים שנקלעו להפסדים וקיים בהם חשש לפיטורי עובדים, בגיבוש תכנית הבראה לכדאיות כלכלית ופוטנציאל צמיחה.",
        "displayedUrl": "https://www.sba.org.il › AidPrograms › Pages",
        "position": 2,
        "title": "קרן לעסקים במצוקה",
        "url": "https://www.sba.org.il/hb/AidPrograms/Pages/pr40.aspx"
      },
      {
        "description": "קרן סיוע למסחר- סוגי קרנות. הסיוע ניתן לסוגי עסקים שונים, למשל, קרן לסיוע במכרזים בינ\"ל, המיועדת ליצואנים ולחברות המעוניינות להרחיב את פעילותן לחו\"ל.",
        "displayedUrl": "https://www.eflow.co.il › trading-assistance-fund",
        "position": 3,
        "title": "קרן סיוע למסחר - מרכז העזרה לעסקים",
        "url": "https://www.eflow.co.il/trading-assistance-fund/"
      },
      {
        "description": "זוהי קרן סיוע מיני רבות, המיועדת לעסקים שעוסקים במסחר בפריפריה הדרומית, באשקלון וקריית מלאכי. כל בעל עסק או יזם שמעוניין להעביר עסק קיים או לפתוח חברה חדשה ...",
        "displayedUrl": "https://loan-israel.co.il › עמוד הבית › קרנות להלוואות לעסקים",
        "position": 4,
        "title": "קרן סיוע למסחר - הלוואות בערבות המדינה ובנקים באישור מיידי",
        "url": "https://loan-israel.co.il/Business/trade-relief-fund/"
      },
      {
        "description": "קרן נתן הינה קרן פילנתרופית לעידוד יזמות באמצעות סיוע במימון להקמת עסק חדש ויחיד. הקרן נוסדה בשנת 2008 בידי נתן קירש (נייתי)",
        "displayedUrl": "https://nksf.org.il",
        "position": 5,
        "title": "קרן נתן: עמוד הבית",
        "url": "https://nksf.org.il/"
      },
      {
        "description": "הסכום המקסימלי להלוואה באישור הקרן לעסקים קטנים ובינוניים הוא 500,000 שקלים, כשבכל מקרה המדינה מעניקה 75-90% מהביטחונות. אנחנו ב- EMG פיננסים מכירים היטב ...",
        "displayedUrl": "https://www.emg-finance.com › קרן-סיוע-לעסקים-קטנים",
        "position": 6,
        "title": "קרן סיוע לעסקים קטנים",
        "url": "https://www.emg-finance.com/%D7%A7%D7%A8%D7%9F-%D7%A1%D7%99%D7%95%D7%A2-%D7%9C%D7%A2%D7%A1%D7%A7%D7%99%D7%9D-%D7%A7%D7%98%D7%A0%D7%99%D7%9D.html"
      },
      {
        "description": "מערך כלי סיוע לתעשייה נועד לסייע לחברות הישראליות לחזק את יכולותיהן השיווקיות בשוק הבין-לאומי בעזרת מספר תכניות מימוניות ייעודיות.",
        "displayedUrl": "https://www.gov.il › topics › govil-landing-page",
        "position": 7,
        "title": "מערך כלי סיוע לתעשייה - Gov.il",
        "url": "https://www.gov.il/he/departments/topics/export-promotion/govil-landing-page"
      },
      {
        "description": "המערך לפיתוח עסקים קטנים של הסוכנות היהודית. Down · ליצירת קשר. - היקפי הסיוע -. 65,242,350. סיוע בסך כולל של מעל 978 מיליון ש\"ח ...",
        "displayedUrl": "https://marom.jewishagency.org",
        "position": 8,
        "title": "מרום - סיוע לעסקים: עמוד הבית",
        "url": "https://marom.jewishagency.org/"
      },
      {
        "description": "מטרת הקרן היא השתתפות בסיכון, שלוקחות החברות הישראליות על עצמן בבואן להתמודד במכרזים בינ\"ל או בביצוע פרויקטים בחו\"ל. כיום קיים פער משמעותי בין היכולות ...",
        "displayedUrl": "https://israel-trade.net › מערך כלי סיוע לתעשייה",
        "position": 9,
        "title": "מערך כלי סיוע לתעשייה: הקרן לפרויקטים ומכרזים בין-לאומיים",
        "url": "https://israel-trade.net/%D7%9B%D7%9C%D7%99-%D7%A1%D7%99%D7%95%D7%A2-2/%D7%94%D7%A7%D7%A8%D7%9F-%D7%9C%D7%A4%D7%A8%D7%95%D7%99%D7%A7%D7%98%D7%99%D7%9D-%D7%95%D7%9E%D7%9B%D7%A8%D7%96%D7%99%D7%9D-%D7%91%D7%99%D7%9F-%D7%9C%D7%90%D7%95%D7%9E%D7%99%D7%99%D7%9D/"
      },
      {
        "description": "קרן נס מנוהלת ע\"י הסוכנות היהודית ומיועדת לסייע באמצעות הלוואה של עד 400,000 ש\"ח ליזמים ובעלי עסקים המעוניינים להקים עסק חדש או להרחיב עסק קיים באזור הנגב.",
        "displayedUrl": "https://www.sba.org.il › AidPrograms › Pages",
        "position": 10,
        "title": "מאגר תכניות וכלי סיוע לעסקים קטנים ובינוניים",
        "url": "https://www.sba.org.il/hb/AidPrograms/Pages/default.aspx"
      }
    ],
    "ai_mode_results": [
      {
        "description": "נכון לשנת 2026, קיימות מספר קרנות ומסלולי סיוע ממשלתיים וציבוריים המיועדים לענף המסחר, ליבואנים וליצואנים בישראל: הקרן להלוואות בערבות המדינה (עסקים קטנים ובינוניים): זוהי הקרן המרכזית המאפשרת לעסקים בענף המסחר לקבל אשראי בתנאים מועדפים. נכון לינואר 2026, קיימים מסלולים ייעודיים הכוללים:מסלול עסקים בהקמה: סיוע ליזמים המעוניינים לפתוח עסק חדש בתחום המסחר.מסלול צפון: הלוואות בתנאים מיוחדים לעסקים הנמצאים בטווח של עד 9 ק\"מ מגבול לבנון, לצורך שיקום וצמיחה.מסלולי השקעה והון חוזר: מיועדים להרחבת פעילות קיימת או לגישור על פערי תזרים.קרן הסיוע בפרויקטים ומכרזים בין-לאומיים: מיועדת לחברות המעוניינות להרחיב את המסחר הבינלאומי שלהן. הקרן משתתפת במימון הגשת הצעות למכרזים בחו\"ל או הוכחת היתכנות לפרויקטים חדשים.מערך כלי סיוע ליצואנים (משרד הכלכלה): כולל תוכניות כמו \"צמיחה לעולם\", מסלול \"יצואן מתחיל\" ומסלול \"יצואן מנוסה\", המעניקים מענקים וליווי מקצועי להגדלת המכירות בחו\"ל.קרנות ייעודיות וסיוע אזורי:קרן נס וקרן הגליל: מעניקות הלוואות ליזמים ובעלי עסקים המקימים או מרחיבים פעילות מסחרית בנגב ובגליל.הטבות מס ביישובי עוטף עזה ושדרות: הוארכו גם לשנת 2026 כדי לתמוך בפעילות הכלכלית באזור.סיוע למשרתי מילואים בעלי עסקים: בשנת 2026 ממשיכה המדינה להפעיל תוכניות לקידום עסקים קטנים ובינוניים של משרתי מילואים ששירתו ב-2025, כולל מענקים וסיוע דרך אתר המילואים של צה\"ל והסוכנות לעסקים קטנים. מומלץ להתעדכן בפרטים המלאים ובאופן הגשת הבקשה דרך האתר הרשמי של קרן ההלוואות בערבות המדינה ודרך אתר הסוכנות לעסקים קטנים ובינוניים.",
        "is_summary": true,
        "position": 0,
        "title": "AI Overview Summary",
        "url": ""
      },
      {
        "description": "אתר זה הינו האתר הרשמי של הקרן, המופעל על ידי אגף החשב הכללי במשרד האוצר. באתר זה תוכלו לקבל מידע נרחב אודות קרן ההלוואות לעסקים ק...",
        "position": 1,
        "title": "קרן ההלוואות לעסקים קטנים ובינוניים בערבות מדינה - govextra",
        "url": "https://govextra.gov.il/mof-gloans/homepage/"
      },
      {
        "description": "19 May 2015 — משרדי הממשלה השונים מעוניינים לתמוך בעסקים הקטנים והחברות הגדולות ועושים את זה במסגרת קרנות סיוע שונות – חלקן מתמקדות ב...",
        "position": 2,
        "title": "קרן סיוע למסחר - הלוואות בערבות המדינה ובנקים באישור מיידי",
        "url": "https://loan-israel.co.il/Business/trade-relief-fund/"
      },
      {
        "description": "11 Dec 2019 — פרסומים · חדשות · חנות התשלומים · מכרזים · הוראות מנכ\"ל · מידע משפטי · דרושים · הסדרים מותנים · חופש המידע · מינהל סחר ...",
        "position": 3,
        "title": "קרן הסיוע בפרויקטים ומכרזים בין-לאומיים - Gov.il",
        "url": "https://www.gov.il/he/departments/publications/Call_for_bids/international-projects-financing#:~:text=%D7%A4%D7%A8%D7%A1%D7%95%D7%9E%D7%99%D7%9D%20%C2%B7%20%D7%97%D7%93%D7%A9%D7%95%D7%AA%20%C2%B7%20%D7%97%D7%A0%D7%95%D7%AA%20%D7%94%D7%AA%D7%A9%D7%9C%D7%95%D7%9E%D7%99%D7%9D%20%C2%B7,%D7%91%D7%9E%D7%99%D7%9E%D7%95%D7%9F%20%D7%94%D7%92%D7%A9%D7%AA%20%D7%94%D7%A6%D7%A2%D7%94%20%D7%9C%D7%9E%D7%9B%D7%A8%D7%96%20%D7%90%D7%95%20%D7%94%D7%95%D7%9B%D7%97%D7%AA%20%D7%94%D7%AA%D7%9B%D7%A0%D7%95%D7%AA"
      },
      {
        "description": "ייעוץ בהקמת עסק הצעד הראשון בין חלום למציאות מתחיל כאן.",
        "position": 4,
        "title": "הסוכנות לעסקים קטנים ובינוניים - מקדמים עסקים ויזמים בישראל",
        "url": "https://www.sba.org.il/#:~:text=%D7%99%D7%99%D7%A2%D7%95%D7%A5%20%D7%91%D7%94%D7%A7%D7%9E%D7%AA%20%D7%A2%D7%A1%D7%A7,%D7%91%D7%99%D7%9F%20%D7%97%D7%9C%D7%95%D7%9D%20%D7%9C%D7%9E%D7%A6%D7%99%D7%90%D7%95%D7%AA%20%D7%9E%D7%AA%D7%97%D7%99%D7%9C%20%D7%9B%D7%90%D7%9F."
      },
      {
        "description": "סיוע לעסקים שנמצאים בקו העימות הצפוני, במרחק של עד 9 ק\"מ מהגבול עם לבנון, בהתאם לרשימת היישובים המפורטת באמצעות הלוואות בערבות מדי...",
        "position": 5,
        "title": "מסלול צפון - govextra",
        "url": "https://govextra.gov.il/mof-gloans/north-track/"
      },
      {
        "description": "15 Apr 2020 — מידע נוסף * אודות האתר * חופש המידע",
        "position": 6,
        "title": "קרן להעמדת הלוואות לעסקים קטנים ובינוניים בערבות המדינה - Gov.il",
        "url": "https://www.gov.il/he/departments/policies/business-loans#:~:text=%D7%9E%D7%99%D7%93%D7%A2%20%D7%A0%D7%95%D7%A1%D7%A3%20*%20%D7%90%D7%95%D7%93%D7%95%D7%AA%20%D7%94%D7%90%D7%AA%D7%A8%20*%20%D7%97%D7%95%D7%A4%D7%A9%20%D7%94%D7%9E%D7%99%D7%93%D7%A2"
      },
      {
        "description": "... ל, בפעימה תשלום התגמולים המרכזית ב-1.5.2026 ובכפוף למדיניות. קידום עסקים קטנים ובינוניים. עידוד, קידום ופיתוח עסקים קטנים ובינ...",
        "position": 7,
        "title": "מדיניות תגמולים, מענקים והטבות למשרתי המילואים - שנת 2025",
        "url": "https://www.miluim.idf.il/articles-list/%D7%9E%D7%93%D7%99%D7%A0%D7%99%D7%95%D7%AA-2025/"
      },
      {
        "description": "קרן נס מנוהלת ע\"י הסוכנות היהודית ומיועדת לסייע באמצעות הלוואה של עד 400,000 ש\"ח ליזמים ובעלי עסקים המעוניינים להקים עסק חדש או לה...",
        "position": 8,
        "title": "קרן נס לפיתוח הנגב - הסוכנות לעסקים קטנים ובינוניים",
        "url": "https://www.sba.org.il/hb/AidPrograms/Pages/pr22.aspx#:~:text=%D7%A7%D7%A8%D7%9F%20%D7%A0%D7%A1%20%D7%9E%D7%A0%D7%95%D7%94%D7%9C%D7%AA%20%D7%A2%22%D7%99,%D7%9C%D7%94%D7%A8%D7%97%D7%99%D7%91%20%D7%A2%D7%A1%D7%A7%20%D7%A7%D7%99%D7%99%D7%9D%20%D7%91%D7%90%D7%96%D7%95%D7%A8%20%D7%94%D7%A0%D7%92%D7%91."
      },
      {
        "description": "קרן הגליל קרן הגליל מיועדת לעידוד פעילות עסקית ויצירת מקומות עבודה באזור הגליל, באמצעות הלוואה של עד 180,000 ₪.",
        "position": 9,
        "title": "מאגר תכניות וכלי סיוע לעסקים קטנים ובינוניים",
        "url": "https://www.sba.org.il/hb/AidPrograms/Pages/default.aspx#:~:text=%D7%A7%D7%A8%D7%9F%20%D7%94%D7%92%D7%9C%D7%99%D7%9C,%D7%94%D7%9C%D7%95%D7%95%D7%90%D7%94%20%D7%A9%D7%9C%20%D7%A2%D7%93%20180%2C000%20%E2%82%AA."
      },
      {
        "description": "20 Dec 2025 — הקרן לסיוע לעסקים קטנים ובינוניים בערבות מדינה - מסלול עסקים בהקמה | לשכת המסחר ת''א והמרכז",
        "position": 10,
        "title": "הקרן לסיוע לעסקים קטנים ובינוניים בערבות מדינה - מסלול עסקים בהקמה",
        "url": "https://www.chamber.org.il/serviceslobby/finance/1430/1851/#:~:text=%D7%94%D7%A7%D7%A8%D7%9F%20%D7%9C%D7%A1%D7%99%D7%95%D7%A2%20%D7%9C%D7%A2%D7%A1%D7%A7%D7%99%D7%9D%20%D7%A7%D7%98%D7%A0%D7%99%D7%9D%20%D7%95%D7%91%D7%99%D7%A0%D7%95%D7%A0%D7%99%D7%99%D7%9D,%D7%9C%D7%A9%D7%9B%D7%AA%20%D7%94%D7%9E%D7%A1%D7%97%D7%A8%20%D7%AA''%D7%90%20%D7%95%D7%94%D7%9E%D7%A8%D7%9B%D7%96"
      },
      {
        "description": "מסלולי הסיוע להגדלת היקף המכירות בחו\"ל * תוכנית פיילוטים בחו\"ל * תכנית צמיחה לעולם * מסלול יצואן מתחיל * מסלול יצואן מנוסה * יצירת...",
        "position": 11,
        "title": "מערך כלי סיוע לתעשייה - Gov.il",
        "url": "https://www.gov.il/he/departments/topics/export-promotion/govil-landing-page#:~:text=%D7%9E%D7%A1%D7%9C%D7%95%D7%9C%D7%99%20%D7%94%D7%A1%D7%99%D7%95%D7%A2%20%D7%9C%D7%94%D7%92%D7%93%D7%9C%D7%AA%20%D7%94%D7%99%D7%A7%D7%A3%20%D7%94%D7%9E%D7%9B%D7%99%D7%A8%D7%95%D7%AA%20%D7%91%D7%97%D7%95%22%D7%9C%20*,*%20%D7%99%D7%A6%D7%99%D7%A8%D7%AA%20%D7%A7%D7%A9%D7%A8%20%D7%A2%D7%9D%20%D7%9E%D7%A2%D7%A8%D7%9A%20%D7%9B%D7%9C%D7%99%20%D7%A1%D7%99%D7%95%D7%A2"
      },
      {
        "description": "5 Jan 2014 — במהלך חודש נובמבר האחרון הוגשו לקרן סיוע בפרויקטים ומכרזים בין-לאומיים 40 בקשות לקבלת מענק. לאחר הליך של בחינת הבקשות או...",
        "position": 12,
        "title": "קרן הסיוע מקדמת את התעשייה הישראלית: 5 מיליון ש\"ח מענק לחברות",
        "url": "https://israel-trade.net/%D7%A7%D7%99%D7%93%D7%95%D7%9D-%D7%A2%D7%A1%D7%A7%D7%99%D7%9D-%D7%99%D7%A9%D7%A8%D7%90%D7%9C%D7%99%D7%99%D7%9D-%D7%94%D7%A7%D7%A8%D7%9F-%D7%9C%D7%A1%D7%99%D7%95%D7%A2-%D7%91%D7%A4%D7%A8%D7%95%D7%99/"
      },
      {
        "description": "29 Dec 2025 — * ועדת הכספים * חקיקה * רצועת עזה",
        "position": 13,
        "title": "אושר בכנסת: הארכת הטבות המס לתושבי שדרות ועוטף עזה לשנת 2026",
        "url": "https://www.port2port.co.il/article/%D7%AA%D7%A2%D7%A9%D7%99%D7%94-%D7%95%D7%A1%D7%97%D7%A8/%D7%AA%D7%A2%D7%A9%D7%99%D7%99%D7%94/%D7%90%D7%95%D7%A9%D7%A8-%D7%91%D7%9B%D7%A0%D7%A1%D7%AA-%D7%94%D7%90%D7%A8%D7%9B%D7%AA-%D7%94%D7%98%D7%91%D7%95%D7%AA-%D7%94%D7%9E%D7%A1-%D7%9C%D7%AA%D7%95%D7%A9%D7%91%D7%99-%D7%A9%D7%93%D7%A8%D7%95%D7%AA-%D7%95%D7%A2%D7%95%D7%98%D7%A3-%D7%A2%D7%96%D7%94-%D7%9C%D7%A9%D7%A0%D7%AA-2026/#:~:text=*%20%D7%95%D7%A2%D7%93%D7%AA%20%D7%94%D7%9B%D7%A1%D7%A4%D7%99%D7%9D%20*%20%D7%97%D7%A7%D7%99%D7%A7%D7%94%20*%20%D7%A8%D7%A6%D7%95%D7%A2%D7%AA%20%D7%A2%D7%96%D7%94"
      }
    ],
    "ai_rank_position": 2,
    "competitor_data": [
      {
        "description": "המידע המלא והמדויק לעניין סוגי ההלוואות שניתן לקחת במסגרת הקרן, תנאי הסף לקבלת הלוואה בקרן והתהליך הנדרש לקבלת הלוואה יתקבל במהלך תהליך הגשת הבקשה ובחינתה, על ...",
        "position": 1,
        "title": "קרן ההלוואות לעסקים קטנים ובינוניים בערבות מדינה - govextra",
        "url": "https://govextra.gov.il/mof-gloans/homepage/"
      },
      {
        "description": "הסוכנות לעסקים קטנים ובינוניים מסייעת באמצעות הלוואות לעסקים שנקלעו להפסדים וקיים בהם חשש לפיטורי עובדים, בגיבוש תכנית הבראה לכדאיות כלכלית ופוטנציאל צמיחה.",
        "position": 2,
        "title": "קרן לעסקים במצוקה",
        "url": "https://www.sba.org.il/hb/AidPrograms/Pages/pr40.aspx"
      },
      {
        "description": "קרן סיוע למסחר- סוגי קרנות. הסיוע ניתן לסוגי עסקים שונים, למשל, קרן לסיוע במכרזים בינ\"ל, המיועדת ליצואנים ולחברות המעוניינות להרחיב את פעילותן לחו\"ל.",
        "position": 3,
        "title": "קרן סיוע למסחר - מרכז העזרה לעסקים",
        "url": "https://www.eflow.co.il/trading-assistance-fund/"
      },
      {
        "description": "זוהי קרן סיוע מיני רבות, המיועדת לעסקים שעוסקים במסחר בפריפריה הדרומית, באשקלון וקריית מלאכי. כל בעל עסק או יזם שמעוניין להעביר עסק קיים או לפתוח חברה חדשה ...",
        "position": 4,
        "title": "קרן סיוע למסחר - הלוואות בערבות המדינה ובנקים באישור מיידי",
        "url": "https://loan-israel.co.il/Business/trade-relief-fund/"
      },
      {
        "description": "קרן נתן הינה קרן פילנתרופית לעידוד יזמות באמצעות סיוע במימון להקמת עסק חדש ויחיד. הקרן נוסדה בשנת 2008 בידי נתן קירש (נייתי)",
        "position": 5,
        "title": "קרן נתן: עמוד הבית",
        "url": "https://nksf.org.il/"
      },
      {
        "description": "הסכום המקסימלי להלוואה באישור הקרן לעסקים קטנים ובינוניים הוא 500,000 שקלים, כשבכל מקרה המדינה מעניקה 75-90% מהביטחונות. אנחנו ב- EMG פיננסים מכירים היטב ...",
        "position": 6,
        "title": "קרן סיוע לעסקים קטנים",
        "url": "https://www.emg-finance.com/%D7%A7%D7%A8%D7%9F-%D7%A1%D7%99%D7%95%D7%A2-%D7%9C%D7%A2%D7%A1%D7%A7%D7%99%D7%9D-%D7%A7%D7%98%D7%A0%D7%99%D7%9D.html"
      },
      {
        "description": "מערך כלי סיוע לתעשייה נועד לסייע לחברות הישראליות לחזק את יכולותיהן השיווקיות בשוק הבין-לאומי בעזרת מספר תכניות מימוניות ייעודיות.",
        "position": 7,
        "title": "מערך כלי סיוע לתעשייה - Gov.il",
        "url": "https://www.gov.il/he/departments/topics/export-promotion/govil-landing-page"
      },
      {
        "description": "המערך לפיתוח עסקים קטנים של הסוכנות היהודית. Down · ליצירת קשר. - היקפי הסיוע -. 65,242,350. סיוע בסך כולל של מעל 978 מיליון ש\"ח ...",
        "position": 8,
        "title": "מרום - סיוע לעסקים: עמוד הבית",
        "url": "https://marom.jewishagency.org/"
      },
      {
        "description": "מטרת הקרן היא השתתפות בסיכון, שלוקחות החברות הישראליות על עצמן בבואן להתמודד במכרזים בינ\"ל או בביצוע פרויקטים בחו\"ל. כיום קיים פער משמעותי בין היכולות ...",
        "position": 9,
        "title": "מערך כלי סיוע לתעשייה: הקרן לפרויקטים ומכרזים בין-לאומיים",
        "url": "https://israel-trade.net/%D7%9B%D7%9C%D7%99-%D7%A1%D7%99%D7%95%D7%A2-2/%D7%94%D7%A7%D7%A8%D7%9F-%D7%9C%D7%A4%D7%A8%D7%95%D7%99%D7%A7%D7%98%D7%99%D7%9D-%D7%95%D7%9E%D7%9B%D7%A8%D7%96%D7%99%D7%9D-%D7%91%D7%99%D7%9F-%D7%9C%D7%90%D7%95%D7%9E%D7%99%D7%99%D7%9D/"
      },
      {
        "description": "קרן נס מנוהלת ע\"י הסוכנות היהודית ומיועדת לסייע באמצעות הלוואה של עד 400,000 ש\"ח ליזמים ובעלי עסקים המעוניינים להקים עסק חדש או להרחיב עסק קיים באזור הנגב.",
        "position": 10,
        "title": "מאגר תכניות וכלי סיוע לעסקים קטנים ובינוניים",
        "url": "https://www.sba.org.il/hb/AidPrograms/Pages/default.aspx"
      }
    ]
  },
  "word_count": 283,
  "wp_post_title": "קרן סיוע למסחר",
  "page_name": "קרן סיוע למסחר",
  "is_special": true
}